Workbook

Sheet Dataset
A1: Company | B1: Sector | C1: Financial Year | D1: Indicator | E1: Category | F1: Value | G1: Unit | H1: Source Document | I1: Page Reference | J1: Notes | K1: Lookup Key (auto)
A2: AECI | B2: Chemicals | C2: FY2025 | D2: Revenue | E2: Financial | F2: 32183 | G2: Rm | H2: AECI 2025 Integrated Report | I2: 9 | J2: Continuing operations | K2: =A2&"|"&D2&"|"&C2 -> AECI|Revenue|FY2025
A3: AECI | B3: Chemicals | C3: FY2024 | D3: Revenue | E3: Financial | F3: 33598 | G3: Rm | H3: AECI 2025 Integrated Report | I3: 9 | J3: Restated comparative shown in FY2025 report | K3: =A3&"|"&D3&"|"&C3 -> AECI|Revenue|FY2024
A4: AECI | B4: Chemicals | C4: FY2025 | D4: EBITDA | E4: Financial | F4: 3412 | G4: Rm | H4: AECI 2025 Integrated Report | I4: 9 | K4: =A4&"|"&D4&"|"&C4 -> AECI|EBITDA|FY2025
A5: AECI | B5: Chemicals | C5: FY2024 | D5: EBITDA | E5: Financial | F5: 3034 | G5: Rm | H5: AECI 2025 Integrated Report | I5: 9 | K5: =A5&"|"&D5&"|"&C5 -> AECI|EBITDA|FY2024
A6: AECI | B6: Chemicals | C6: FY2025 | D6: EBITDA margin | E6: Financial | F6: 11 | G6: % | H6: AECI 2025 Integrated Report | I6: 9 | K6: =A6&"|"&D6&"|"&C6 -> AECI|EBITDA margin|FY2025
A7: AECI | B7: Chemicals | C7: FY2024 | D7: EBITDA margin | E7: Financial | F7: 9 | G7: % | H7: AECI 2025 Integrated Report | I7: 9 | K7: =A7&"|"&D7&"|"&C7 -> AECI|EBITDA margin|FY2024
A8: AECI | B8: Chemicals | C8: FY2025 | D8: HEPS | E8: Financial | F8: 1068 | G8: cents | H8: AECI 2025 Integrated Report | I8: 9 | K8: =A8&"|"&D8&"|"&C8 -> AECI|HEPS|FY2025
A9: AECI | B9: Chemicals | C9: FY2024 | D9: HEPS | E9: Financial | F9: 716 | G9: cents | H9: AECI 2025 Integrated Report | I9: 9 | K9: =A9&"|"&D9&"|"&C9 -> AECI|HEPS|FY2024
A10: AECI | B10: Chemicals | C10: FY2025 | D10: Net debt | E10: Financial | F10: 0.5 | G10: R billion | H10: AECI 2025 Integrated Report | I10: 9 | K10: =A10&"|"&D10&"|"&C10 -> AECI|Net debt|FY2025
A11: AECI | B11: Chemicals | C11: FY2024 | D11: Net debt | E11: Financial | F11: 3.7 | G11: R billion | H11: AECI 2025 Integrated Report | I11: 9 | K11: =A11&"|"&D11&"|"&C11 -> AECI|Net debt|FY2024
A12: AECI | B12: Chemicals | C12: FY2025 | D12: ROIC | E12: Financial | F12: 13 | G12: % | H12: AECI 2025 Integrated Report | I12: 9 | K12: =A12&"|"&D12&"|"&C12 -> AECI|ROIC|FY2025
A13: AECI | B13: Chemicals | C13: FY2024 | D13: ROIC | E13: Financial | F13: 9 | G13: % | H13: AECI 2025 Integrated Report | I13: 9 | K13: =A13&"|"&D13&"|"&C13 -> AECI|ROIC|FY2024
A14: AECI | B14: Chemicals | C14: FY2025 | D14: Total dividend | E14: Financial | F14: 228 | G14: cents per share | H14: AECI 2025 Integrated Report | I14: 9 | K14: =A14&"|"&D14&"|"&C14 -> AECI|Total dividend|FY2025
A15: AECI | B15: Chemicals | C15: FY2024 | D15: Total dividend | E15: Financial | F15: 219 | G15: cents per share | H15: AECI 2025 Integrated Report | I15: 9 | K15: =A15&"|"&D15&"|"&C15 -> AECI|Total dividend|FY2024
A16: AECI | B16: Chemicals | C16: FY2022 | D16: EBITDA (core) | E16: Financial | F16: 3100 | G16: Rm | H16: AECI 2025 Integrated Report | I16: 13 | J16: Baseline year in strategy KPI table | K16: =A16&"|"&D16&"|"&C16 -> AECI|EBITDA (core)|FY2022
A17: AECI | B17: Chemicals | C17: FY2023 | D17: EBITDA (core) | E17: Financial | F17: 3401 | G17: Rm | H17: AECI 2025 Integrated Report | I17: 13 | K17: =A17&"|"&D17&"|"&C17 -> AECI|EBITDA (core)|FY2023
A18: AECI | B18: Chemicals | C18: FY2024 | D18: EBITDA (core) | E18: Financial | F18: 2957 | G18: Rm | H18: AECI 2025 Integrated Report | I18: 13 | K18: =A18&"|"&D18&"|"&C18 -> AECI|EBITDA (core)|FY2024
A19: AECI | B19: Chemicals | C19: FY2025 | D19: EBITDA (core) | E19: Financial | F19: 3248 | G19: Rm | H19: AECI 2025 Integrated Report | I19: 13 | K19: =A19&"|"&D19&"|"&C19 -> AECI|EBITDA (core)|FY2025
A20: AECI | B20: Chemicals | C20: FY2022 | D20: ROIC (strategy KPI) | E20: Financial | F20: 12 | G20: % | H20: AECI 2025 Integrated Report | I20: 13 | K20: =A20&"|"&D20&"|"&C20 -> AECI|ROIC (strategy KPI)|FY2022
A21: AECI | B21: Chemicals | C21: FY2023 | D21: ROIC (strategy KPI) | E21: Financial | F21: 14 | G21: % | H21: AECI 2025 Integrated Report | I21: 13 | K21: =A21&"|"&D21&"|"&C21 -> AECI|ROIC (strategy KPI)|FY2023
A22: AECI | B22: Chemicals | C22: FY2024 | D22: ROIC (strategy KPI) | E22: Financial | F22: 15 | G22: % | H22: AECI 2025 Integrated Report | I22: 13 | K22: =A22&"|"&D22&"|"&C22 -> AECI|ROIC (strategy KPI)|FY2024
A23: AECI | B23: Chemicals | C23: FY2025 | D23: ROIC (strategy KPI) | E23: Financial | F23: 16 | G23: % | H23: AECI 2025 Integrated Report | I23: 13 | K23: =A23&"|"&D23&"|"&C23 -> AECI|ROIC (strategy KPI)|FY2025
A24: AECI | B24: Chemicals | C24: FY2022 | D24: Net debt/EBITDA | E24: Financial | F24: -1.5 | G24: x | H24: AECI 2025 Integrated Report | I24: 13 | K24: =A24&"|"&D24&"|"&C24 -> AECI|Net debt/EBITDA|FY2022
A25: AECI | B25: Chemicals | C25: FY2023 | D25: Net debt/EBITDA | E25: Financial | F25: 1.2 | G25: x | H25: AECI 2025 Integrated Report | I25: 13 | K25: =A25&"|"&D25&"|"&C25 -> AECI|Net debt/EBITDA|FY2023
A26: AECI | B26: Chemicals | C26: FY2024 | D26: Net debt/EBITDA | E26: Financial | F26: 1.2 | G26: x | H26: AECI 2025 Integrated Report | I26: 13 | K26: =A26&"|"&D26&"|"&C26 -> AECI|Net debt/EBITDA|FY2024
A27: AECI | B27: Chemicals | C27: FY2025 | D27: Net debt/EBITDA | E27: Financial | F27: 0.1 | G27: x | H27: AECI 2025 Integrated Report | I27: 13 | K27: =A27&"|"&D27&"|"&C27 -> AECI|Net debt/EBITDA|FY2025
A28: AECI | B28: Chemicals | C28: FY2025 | D28: TRIR (Total Recordable Injury Rate) | E28: Social | F28: 0.2 | G28: rate | H28: AECI 2025 Integrated Report | I28: 9 | K28: =A28&"|"&D28&"|"&C28 -> AECI|TRIR (Total Recordable Injury Rate)|FY2025
... A37: AECI | B37: Chemicals | C37: FY2024 | D37: Scope 3 GHG emissions | E37: Environmental | F37: 1081153 | G37: tCO2e | H37: AECI 2025 Integrated Report | I37: 9 | K37: =A37&"|"&D37&"|"&C37 -> AECI|Scope 3 GHG emissions|FY2024
A38: AECI | B38: Chemicals | C38: FY2025 | D38: Total carbon footprint (Scope 1+2) | E38: Environmental | F38: =F32+F34 -> 365500 | G38: tCO2e | H38: AECI 2025 Integrated Report | I38: 9 | J38: [Formula: Scope 1 + Scope 2, linked to rows above] | K38: =A38&"|"&D38&"|"&C38 -> AECI|Total carbon footprint (Scope 1+2)|FY2025
A39: AECI | B39: Chemicals | C39: FY2024 | D39: Total carbon footprint (Scope 1+2) | E39: Environmental | F39: =F33+F35 -> 416337 | G39: tCO2e | H39: AECI 2025 Integrated Report | I39: 9 | J39: [Formula: Scope 1 + Scope 2, linked to rows above] | K39: =A39&"|"&D39&"|"&C39 -> AECI|Total carbon footprint (Scope 1+2)|FY2024
A40: AECI | B40: Chemicals | C40: FY2025 | D40: Hazardous waste disposed | E40: Environmental | F40: 9943 | G40: tonnes | H40: AECI 2025 Integrated Report | I40: 9 | K40: =A40&"|"&D40&"|"&C40 -> AECI|Hazardous waste disposed|FY2025
A41: AECI | B41: Chemicals | C41: FY2024 | D41: Hazardous waste disposed | E41: Environmental | F41: 12722 | G41: tonnes | H41: AECI 2025 Integrated Report | I41: 9 | K41: =A41&"|"&D41&"|"&C41 -> AECI|Hazardous waste disposed|FY2024
A42: AECI | B42: Chemicals | C42: FY2025 | D42: Renewable electricity | E42: Environmental | F42: 16669 | G42: MWh | H42: AECI 2025 Integrated Report | I42: 9 | K42: =A42&"|"&D42&"|"&C42 -> AECI|Renewable electricity|FY2025
A43: AECI | B43: Chemicals | C43: FY2024 | D43: Renewable electricity | E43: Environmental | F43: 8663 | G43: MWh | H43: AECI 2025 Integrated Report | I43: 9 | K43: =A43&"|"&D43&"|"&C43 -> AECI|Renewable electricity|FY2024
A44: AECI | B44: Chemicals | C44: FY2025 | D44: Female representation, top/senior/middle mgmt | E44: Social | F44: 30 | G44: % | H44: AECI 2025 Integrated Report | I44: 9 | K44: =A44&"|"&D44&"|"&C44 -> AECI|Female representation, top/senior/middle mgmt|FY2025
A45: AECI | B45: Chemicals | C45: FY2024 | D45: Female representation, top/senior/middle mgmt | E45: Social | F45: 29 | G45: % | H45: AECI 2025 Integrated Report | I45: 9 | K45: =A45&"|"&D45&"|"&C45 -> AECI|Female representation, top/senior/middle mgmt|FY2024
A46: AECI | B46: Chemicals | C46: FY2025 | D46: Total employees | E46: Social | F46: 5459 | G46: number | H46: AECI 2025 Integrated Report | I46: 11 | J46: Across >20 countries | K46: =A46&"|"&D46&"|"&C46 -> AECI|Total employees|FY2025
A47: AECI | B47: Chemicals | C47: FY2025 | D47: Social responsibility spend | E47: Social | F47: 33 | G47: Rm | H47: AECI 2025 Integrated Report | I47: 9 | K47: =A47&"|"&D47&"|"&C47 -> AECI|Social responsibility spend|FY2025
A48: AECI | B48: Chemicals | C48: FY2024 | D48: Social responsibility spend | E48: Social | F48: 28.5 | G48: Rm | H48: AECI 2025 Integrated Report | I48: 9 | K48: =A48&"|"&D48&"|"&C48 -> AECI|Social responsibility spend|FY2024
A49: ArcelorMittal SA | B49: Steel / Basic Materials | C49: FY2021 | D49: Employee & contractor fatalities | E49: Social | F49: 6 | G49: number | H49: ArcelorMittal SA 2025 Integrated Report | I49: 9 | J49: 5-year KPI table | K49: =A49&"|"&D49&"|"&C49 -> ArcelorMittal SA|Employee & contractor fatalities|FY2021
A50: ArcelorMittal SA | B50: Steel / Basic Materials | C50: FY2021 | D50: LTIFR | E50: Social | F50: 0.98 | G50: rate | H50: ArcelorMittal SA 2025 Integrated Report | I50: 9 | K50: =A50&"|"&D50&"|"&C50 -> ArcelorMittal SA|LTIFR|FY2021
A51: ArcelorMittal SA | B51: Steel / Basic Materials | C51: FY2021 | D51: TIFR | E51: Social | F51: 7.8 | G51: rate | H51: ArcelorMittal SA 2025 Integrated Report | I51: 9 | K51: =A51&"|"&D51&"|"&C51 -> ArcelorMittal SA|TIFR|FY2021
A52: ArcelorMittal SA | B52: Steel / Basic Materials | C52: FY2021 | D52: EBITDA per tonne sold | E52: Financial | F52: 3465 | G52: R/t | H52: ArcelorMittal SA 2025 Integrated Report | I52: 9 | K52: =A52&"|"&D52&"|"&C52 -> ArcelorMittal SA|EBITDA per tonne sold|FY2021
A53: ArcelorMittal SA | B53: Steel / Basic Materials | C53: FY2021 | D53: Return on capital employed | E53: Financial | F53: 53.9 | G53: % | H53: ArcelorMittal SA 2025 Integrated Report | I53: 9 | K53: =A53&"|"&D53&"|"&C53 -> ArcelorMittal SA|Return on capital employed|FY2021
A54: ArcelorMittal SA | B54: Steel / Basic Materials | C54: FY2021 | D54: Steel market share | E54: Financial | F54: 47 | G54: % | H54: ArcelorMittal SA 2025 Integrated Report | I54: 9 | K54: =A54&"|"&D54&"|"&C54 -> ArcelorMittal SA|Steel market share|FY2021
A55: ArcelorMittal SA | B55: Steel / Basic Materials | C55: FY2021 | D55: Crude steel production | E55: Operational | F55: 3096 | G55: kt/y | H55: ArcelorMittal SA 2025 Integrated Report | I55: 9 | K55: =A55&"|"&D55&"|"&C55 -> ArcelorMittal SA|Crude steel production|FY2021
A56: ArcelorMittal SA | B56: Steel / Basic Materials | C56: FY2021 | D56: Cash generated from operations (pre working cap) | E56: Financial | F56: 9144 | G56: Rm | H56: ArcelorMittal SA 2025 Integrated Report | I56: 9 | K56: =A56&"|"&D56&"|"&C56 -> ArcelorMittal SA|Cash generated from operations (pre working cap)|FY2021
A57: ArcelorMittal SA | B57: Steel / Basic Materials | C57: FY2021 | D57: Net debt position | E57: Financial | F57: 1258 | G57: Rm | H57: ArcelorMittal SA 2025 Integrated Report | I57: 9 | K57: =A57&"|"&D57&"|"&C57 -> ArcelorMittal SA|Net debt position|FY2021
A58: ArcelorMittal SA | B58: Steel / Basic Materials | C58: FY2021 | D58: Preferential procurement spend | E58: Social | F58: 15.4 | G58: Rbn | H58: ArcelorMittal SA 2025 Integrated Report | I58: 9 | K58: =A58&"|"&D58&"|"&C58 -> ArcelorMittal SA|Preferential procurement spend|FY2021
A59: ArcelorMittal SA | B59: Steel / Basic Materials | C59: FY2021 | D59: B-BBEE compliance score | E59: Social | F59: 8 | G59: rating | H59: ArcelorMittal SA 2025 Integrated Report | I59: 9 | J59: 2025 figure self-assessed | K59: =A59&"|"&D59&"|"&C59 -> ArcelorMittal SA|B-BBEE compliance score|FY2021
A60: ArcelorMittal SA | B60: Steel / Basic Materials | C60: FY2021 | D60: Environmental spend | E60: Environmental | F60: 64 | G60: Rm | H60: ArcelorMittal SA 2025 Integrated Report | I60: 9 | K60: =A60&"|"&D60&"|"&C60 -> ArcelorMittal SA|Environmental spend|FY2021
A61: ArcelorMittal SA | B61: Steel / Basic Materials | C61: FY2021 | D61: CO2 emissions intensity | E61: Environmental | F61: 2.72 | G61: tCO2e/t liquid steel | H61: ArcelorMittal SA 2025 Integrated Report | I61: 9 | K61: =A61&"|"&D61&"|"&C61 -> ArcelorMittal SA|CO2 emissions intensity|FY2021
A62: ArcelorMittal SA | B62: Steel / Basic Materials | C62: FY2021 | D62: Total cost of employment | E62: Social | F62: 4875 | G62: Rm | H62: ArcelorMittal SA 2025 Integrated Report | I62: 9 | K62: =A62&"|"&D62&"|"&C62 -> ArcelorMittal SA|Total cost of employment|FY2021
A63: ArcelorMittal SA | B63: Steel / Basic Materials | C63: FY2022 | D63: Employee & contractor fatalities | E63: Social | F63: 2 | G63: number | H63: ArcelorMittal SA 2025 Integrated Report | I63: 9 | J63: 5-year KPI table | K63: =A63&"|"&D63&"|"&C63 -> ArcelorMittal SA|Employee & contractor fatalities|FY2022
A64: ArcelorMittal SA | B64: Steel / Basic Materials | C64: FY2022 | D64: LTIFR | E64: Social | F64: 0.87 | G64: rate | H64: ArcelorMittal SA 2025 Integrated Report | I64: 9 | K64: =A64&"|"&D64&"|"&C64 -> ArcelorMittal SA|LTIFR|FY2022
A65: ArcelorMittal SA | B65: Steel / Basic Materials | C65: FY2022 | D65: TIFR | E65: Social | F65: 5.74 | G65: rate | H65: ArcelorMittal SA 2025 Integrated Report | I65: 9 | K65: =A65&"|"&D65&"|"&C65 -> ArcelorMittal SA|TIFR|FY2022
A66: ArcelorMittal SA | B66: Steel / Basic Materials | C66: FY2022 | D66: EBITDA per tonne sold | E66: Financial | F66: 1977 | G66: R/t | H66: ArcelorMittal SA 2025 Integrated Report | I66: 9 | K66: =A66&"|"&D66&"|"&C66 -> ArcelorMittal SA|EBITDA per tonne sold|FY2022
A67: ArcelorMittal SA | B67: Steel / Basic Materials | C67: FY2022 | D67: Return on capital employed | E67: Financial | F67: 20.32 | G67: % | H67: ArcelorMittal SA 2025 Integrated Report | I67: 9 | K67: =A67&"|"&D67&"|"&C67 -> ArcelorMittal SA|Return on capital employed|FY2022
A68: ArcelorMittal SA | B68: Steel / Basic Materials | C68: FY2022 | D68: Steel market share | E68: Financial | F68: 46 | G68: % | H68: ArcelorMittal SA 2025 Integrated Report | I68: 9 | K68: =A68&"|"&D68&"|"&C68 -> ArcelorMittal SA|Steel market share|FY2022
A69: ArcelorMittal SA | B69: Steel / Basic Materials | C69: FY2022 | D69: Crude steel production | E69: Operational | F69: 2465 | G69: kt/y | H69: ArcelorMittal SA 2025 Integrated Report | I69: 9 | K69: =A69&"|"&D69&"|"&C69 -> ArcelorMittal SA|Crude steel production|FY2022
A70: ArcelorMittal SA | B70: Steel / Basic Materials | C70: FY2022 | D70: Cash generated from operations (pre working cap) | E70: Financial | F70: 4260 | G70: Rm | H70: ArcelorMittal SA 2025 Integrated Report | I70: 9 | K70: =A70&"|"&D70&"|"&C70 -> ArcelorMittal SA|Cash generated from operations (pre working cap)|FY2022
A71: ArcelorMittal SA | B71: Steel / Basic Materials | C71: FY2022 | D71: Net debt position | E71: Financial | F71: 2808 | G71: Rm | H71: ArcelorMittal SA 2025 Integrated Report | I71: 9 | K71: =A71&"|"&D71&"|"&C71 -> ArcelorMittal SA|Net debt position|FY2022
A72: ArcelorMittal SA | B72: Steel / Basic Materials | C72: FY2022 | D72: Preferential procurement spend | E72: Social | F72: 16.8 | G72: Rbn | H72: ArcelorMittal SA 2025 Integrated Report | I72: 9 | K72: =A72&"|"&D72&"|"&C72 -> ArcelorMittal SA|Preferential procurement spend|FY2022
A73: ArcelorMittal SA | B73: Steel / Basic Materials | C73: FY2022 | D73: B-BBEE compliance score | E73: Social | F73: 5 | G73: rating | H73: ArcelorMittal SA 2025 Integrated Report | I73: 9 | J73: 2025 figure self-assessed | K73: =A73&"|"&D73&"|"&C73 -> ArcelorMittal SA|B-BBEE compliance score|FY2022
A74: ArcelorMittal SA | B74: Steel / Basic Materials | C74: FY2022 | D74: Environmental spend | E74: Environmental | F74: 301 | G74: Rm | H74: ArcelorMittal SA 2025 Integrated Report | I74: 9 | K74: =A74&"|"&D74&"|"&C74 -> ArcelorMittal SA|Environmental spend|FY2022
A75: ArcelorMittal SA | B75: Steel / Basic Materials | C75: FY2022 | D75: CO2 emissions intensity | E75: Environmental | F75: 3.39 | G75: tCO2e/t liquid steel | H75: ArcelorMittal SA 2025 Integrated Report | I75: 9 | K75: =A75&"|"&D75&"|"&C75 -> ArcelorMittal SA|CO2 emissions intensity|FY2022
A76: ArcelorMittal SA | B76: Steel / Basic Materials | C76: FY2022 | D76: Total cost of employment | E76: Social | F76: 4959 | G76: Rm | H76: ArcelorMittal SA 2025 Integrated Report | I76: 9 | K76: =A76&"|"&D76&"|"&C76 -> ArcelorMittal SA|Total cost of employment|FY2022
A77: ArcelorMittal SA | B77: Steel / Basic Materials | C77: FY2023 | D77: Employee & contractor fatalities | E77: Social | F77: 1 | G77: number | H77: ArcelorMittal SA 2025 Integrated Report | I77: 9 | J77: 5-year KPI table | K77: =A77&"|"&D77&"|"&C77 -> ArcelorMittal SA|Employee & contractor fatalities|FY2023
A78: ArcelorMittal SA | B78: Steel / Basic Materials | C78: FY2023 | D78: LTIFR | E78: Social | F78: 0.77 | G78: rate | H78: ArcelorMittal SA 2025 Integrated Report | I78: 9 | K78: =A78&"|"&D78&"|"&C78 -> ArcelorMittal SA|LTIFR|FY2023
A79: ArcelorMittal SA | B79: Steel / Basic Materials | C79: FY2023 | D79: TIFR | E79: Social | F79: 7.69 | G79: rate | H79: ArcelorMittal SA 2025 Integrated Report | I79: 9 | K79: =A79&"|"&D79&"|"&C79 -> ArcelorMittal SA|TIFR|FY2023
A80: ArcelorMittal SA | B80: Steel / Basic Materials | C80: FY2023 | D80: EBITDA per tonne sold | E80: Financial | F80: 23 | G80: R/t | H80: ArcelorMittal SA 2025 Integrated Report | I80: 9 | K80: =A80&"|"&D80&"|"&C80 -> ArcelorMittal SA|EBITDA per tonne sold|FY2023
A81: ArcelorMittal SA | B81: Steel / Basic Materials | C81: FY2023 | D81: Return on capital employed | E81: Financial | F81: -2.16 | G81: % | H81: ArcelorMittal SA 2025 Integrated Report | I81: 9 | K81: =A81&"|"&D81&"|"&C81 -> ArcelorMittal SA|Return on capital employed|FY2023
A82: ArcelorMittal SA | B82: Steel / Basic Materials | C82: FY2023 | D82: Steel market share | E82: Financial | F82: 46 | G82: % | H82: ArcelorMittal SA 2025 Integrated Report | I82: 9 | K82: =A82&"|"&D82&"|"&C82 -> ArcelorMittal SA|Steel market share|FY2023
A83: ArcelorMittal SA | B83: Steel / Basic Materials | C83: FY2023 | D83: Crude steel production | E83: Operational | F83: 2817 | G83: kt/y | H83: ArcelorMittal SA 2025 Integrated Report | I83: 9 | K83: =A83&"|"&D83&"|"&C83 -> ArcelorMittal SA|Crude steel production|FY2023
A84: ArcelorMittal SA | B84: Steel / Basic Materials | C84: FY2023 | D84: Cash generated from operations (pre working cap) | E84: Financial | F84: 246 | G84: Rm | H84: ArcelorMittal SA 2025 Integrated Report | I84: 9 | K84: =A84&"|"&D84&"|"&C84 -> ArcelorMittal SA|Cash generated from operations (pre working cap)|FY2023
A85: ArcelorMittal SA | B85: Steel / Basic Materials | C85: FY2023 | D85: Net debt position | E85: Financial | F85: 3215 | G85: Rm | H85: ArcelorMittal SA 2025 Integrated Report | I85: 9 | K85: =A85&"|"&D85&"|"&C85 -> ArcelorMittal SA|Net debt position|FY2023
A86: ArcelorMittal SA | B86: Steel / Basic Materials | C86: FY2023 | D86: Preferential procurement spend | E86: Social | F86: 19.7 | G86: Rbn | H86: ArcelorMittal SA 2025 Integrated Report | I86: 9 | K86: =A86&"|"&D86&"|"&C86 -> ArcelorMittal SA|Preferential procurement spend|FY2023
A87: ArcelorMittal SA | B87: Steel / Basic Materials | C87: FY2023 | D87: B-BBEE compliance score | E87: Social | F87: 6 | G87: rating | H87: ArcelorMittal SA 2025 Integrated Report | I87: 9 | J87: 2025 figure self-assessed | K87: =A87&"|"&D87&"|"&C87 -> ArcelorMittal SA|B-BBEE compliance score|FY2023
A88: ArcelorMittal SA | B88: Steel / Basic Materials | C88: FY2023 | D88: Environmental spend | E88: Environmental | F88: 269 | G88: Rm | H88: ArcelorMittal SA 2025 Integrated Report | I88: 9 | K88: =A88&"|"&D88&"|"&C88 -> ArcelorMittal SA|Environmental spend|FY2023
A89: ArcelorMittal SA | B89: Steel / Basic Materials | C89: FY2023 | D89: CO2 emissions intensity | E89: Environmental | F89: 3.38 | G89: tCO2e/t liquid steel | H89: ArcelorMittal SA 2025 Integrated Report | I89: 9 | K89: =A89&"|"&D89&"|"&C89 -> ArcelorMittal SA|CO2 emissions intensity|FY2023
A90: ArcelorMittal SA | B90: Steel / Basic Materials | C90: FY2023 | D90: Total cost of employment | E90: Social | F90: 5053 | G90: Rm | H90: ArcelorMittal SA 2025 Integrated Report | I90: 9 | K90: =A90&"|"&D90&"|"&C90 -> ArcelorMittal SA|Total cost of employment|FY2023
A91: ArcelorMittal SA | B91: Steel / Basic Materials | C91: FY2024 | D91: Employee & contractor fatalities | E91: Social | F91: 1 | G91: number | H91: ArcelorMittal SA 2025 Integrated Report | I91: 9 | J91: 5-year KPI table | K91: =A91&"|"&D91&"|"&C91 -> ArcelorMittal SA|Employee & contractor fatalities|FY2024
A92: ArcelorMittal SA | B92: Steel / Basic Materials | C92: FY2024 | D92: LTIFR | E92: Social | F92: 1.13 | G92: rate | H92: ArcelorMittal SA 2025 Integrated Report | I92: 9 | K92: =A92&"|"&D92&"|"&C92 -> ArcelorMittal SA|LTIFR|FY2024
A93: ArcelorMittal SA | B93: Steel / Basic Materials | C93: FY2024 | D93: TIFR | E93: Social | F93: 7.16 | G93: rate | H93: ArcelorMittal SA 2025 Integrated Report | I93: 9 | K93: =A93&"|"&D93&"|"&C93 -> ArcelorMittal SA|TIFR|FY2024
A94: ArcelorMittal SA | B94: Steel / Basic Materials | C94: FY2024 | D94: EBITDA per tonne sold | E94: Financial | F94: -1295 | G94: R/t | H94: ArcelorMittal SA 2025 Integrated Report | I94: 9 | K94: =A94&"|"&D94&"|"&C94 -> ArcelorMittal SA|EBITDA per tonne sold|FY2024
A95: ArcelorMittal SA | B95: Steel / Basic Materials | C95: FY2024 | D95: Return on capital employed | E95: Financial | F95: -22.65 | G95: % | H95: ArcelorMittal SA 2025 Integrated Report | I95: 9 | K95: =A95&"|"&D95&"|"&C95 -> ArcelorMittal SA|Return on capital employed|FY2024
A96: ArcelorMittal SA | B96: Steel / Basic Materials | C96: FY2024 | D96: Steel market share | E96: Financial | F96: 46 | G96: % | H96: ArcelorMittal SA 2025 Integrated Report | I96: 9 | K96: =A96&"|"&D96&"|"&C96 -> ArcelorMittal SA|Steel market share|FY2024
A97: ArcelorMittal SA | B97: Steel / Basic Materials | C97: FY2024 | D97: Crude steel production | E97: Operational | F97: 2589 | G97: kt/y | H97: ArcelorMittal SA 2025 Integrated Report | I97: 9 | K97: =A97&"|"&D97&"|"&C97 -> ArcelorMittal SA|Crude steel production|FY2024
A98: ArcelorMittal SA | B98: Steel / Basic Materials | C98: FY2024 | D98: Cash generated from operations (pre working cap) | E98: Financial | F98: -1973 | G98: Rm | H98: ArcelorMittal SA 2025 Integrated Report | I98: 9 | K98: =A98&"|"&D98&"|"&C98 -> ArcelorMittal SA|Cash generated from operations (pre working cap)|FY2024
A99: ArcelorMittal SA | B99: Steel / Basic Materials | C99: FY2024 | D99: Net debt position | E99: Financial | F99: 5111 | G99: Rm | H99: ArcelorMittal SA 2025 Integrated Report | I99: 9 | K99: =A99&"|"&D99&"|"&C99 -> ArcelorMittal SA|Net debt position|FY2024
A100: ArcelorMittal SA | B100: Steel / Basic Materials | C100: FY2024 | D100: Preferential procurement spend | E100: Social | F100: 20 | G100: Rbn | H100: ArcelorMittal SA 2025 Integrated Report | I100: 9 | K100: =A100&"|"&D100&"|"&C100 -> ArcelorMittal SA|Preferential procurement spend|FY2024
A101: ArcelorMittal SA | B101: Steel / Basic Materials | C101: FY2024 | D101: B-BBEE compliance score | E101: Social | F101: 8 | G101: rating | H101: ArcelorMittal SA 2025 Integrated Report | I101: 9 | J101: 2025 figure self-assessed | K101: =A101&"|"&D101&"|"&C101 -> ArcelorMittal SA|B-BBEE compliance score|FY2024
A102: ArcelorMittal SA | B102: Steel / Basic Materials | C102: FY2024 | D102: Environmental spend | E102: Environmental | F102: 237 | G102: Rm | H102: ArcelorMittal SA 2025 Integrated Report | I102: 9 | K102: =A102&"|"&D102&"|"&C102 -> ArcelorMittal SA|Environmental spend|FY2024
A103: ArcelorMittal SA | B103: Steel / Basic Materials | C103: FY2024 | D103: CO2 emissions intensity | E103: Environmental | F103: 3.35 | G103: tCO2e/t liquid steel | H103: ArcelorMittal SA 2025 Integrated Report | I103: 9 | K103: =A103&"|"&D103&"|"&C103 -> ArcelorMittal SA|CO2 emissions intensity|FY2024
A104: ArcelorMittal SA | B104: Steel / Basic Materials | C104: FY2024 | D104: Total cost of employment | E104: Social | F104: 4961 | G104: Rm | H104: ArcelorMittal SA 2025 Integrated Report | I104: 9 | K104: =A104&"|"&D104&"|"&C104 -> ArcelorMittal SA|Total cost of employment|FY2024
A105: ArcelorMittal SA | B105: Steel / Basic Materials | C105: FY2025 | D105: Employee & contractor fatalities | E105: Social | F105: 1 | G105: number | H105: ArcelorMittal SA 2025 Integrated Report | I105: 9 | J105: 5-year KPI table | K105: =A105&"|"&D105&"|"&C105 -> ArcelorMittal SA|Employee & contractor fatalities|FY2025
A106: ArcelorMittal SA | B106: Steel / Basic Materials | C106: FY2025 | D106: LTIFR | E106: Social | F106: 0.62 | G106: rate | H106: ArcelorMittal SA 2025 Integrated Report | I106: 9 | K106: =A106&"|"&D106&"|"&C106 -> ArcelorMittal SA|LTIFR|FY2025
A107: ArcelorMittal SA | B107: Steel / Basic Materials | C107: FY2025 | D107: TIFR | E107: Social | F107: 6.8 | G107: rate | H107: ArcelorMittal SA 2025 Integrated Report | I107: 9 | K107: =A107&"|"&D107&"|"&C107 -> ArcelorMittal SA|TIFR|FY2025
A108: ArcelorMittal SA | B108: Steel / Basic Materials | C108: FY2025 | D108: EBITDA per tonne sold | E108: Financial | F108: -546 | G108: R/t | H108: ArcelorMittal SA 2025 Integrated Report | I108: 9 | K108: =A108&"|"&D108&"|"&C108 -> ArcelorMittal SA|EBITDA per tonne sold|FY2025
...

Sheet Data Dictionary
A1: Variable | B1: Definition | C1: Measurement / Unit | D1: Capital (IIRC Six Capitals) | E1: Category | F1: Data Type | G1: Source Type
A2: Revenue | B2: Total revenue/turnover/sales reported in the consolidated income statement | C2: Rm / US$m | D2: Financial | E2: Financial performance | F2: Continuous (numeric) | G2: Integrated report, audited financial statements section
A3: EBITDA / Adjusted EBITDA | B3: Earnings before interest, tax, depreciation and amortisation, as defined by each company | C3: Rm / US$m | D3: Financial | E3: Financial performance | F3: Continuous (numeric) | G3: Integrated report, financial highlights / CFO report
A4: HEPS (Headline Earnings Per Share) | B4: Headline earnings attributable to ordinary shareholders divided by the weighted average number of shares in issue, per JSE/SAICA Circular definition | C4: cents / US cents | D4: Financial | E4: Financial performance | F4: Continuous (numeric) | G4: Integrated report, financial highlights
A5: Net debt / Net debt position | B5: Total interest-bearing borrowings less cash and cash equivalents | C5: Rm / R billion | D5: Financial | E5: Financial performance | F5: Continuous (numeric) | G5: Integrated report, financial highlights
A6: ROIC / ROCE | B6: Return on Invested Capital / Return on Capital Employed, company-specific formula, generally NOPAT (or operating profit) divided by average invested capital | C6: % | D6: Financial | E6: Financial performance | F6: Continuous (numeric) | G6: Integrated report, strategy/KPI table
A7: Scope 1 GHG emissions | B7: Direct greenhouse gas emissions from owned or controlled sources, reported per the GHG Protocol | C7: tCO2e | D7: Natural | E7: Environmental / climate | F7: Continuous (numeric) | G7: Integrated / sustainability report, ESG data table
A8: Scope 2 GHG emissions | B8: Indirect GHG emissions from the generation of purchased electricity, steam, heat or cooling consumed | C8: tCO2e | D8: Natural | E8: Environmental / climate | F8: Continuous (numeric) | G8: Integrated / sustainability report, ESG data table
A9: Scope 3 GHG emissions | B9: Other indirect GHG emissions occurring in a company's value chain | C9: tCO2e | D9: Natural | E9: Environmental / climate | F9: Continuous (numeric) | G9: Integrated / sustainability report, ESG data table (where disclosed)
A10: GHG emission reduction vs baseline | B10: Percentage reduction in emissions achieved against a stated historical baseline year, as reported by the company toward its stated target | C10: % reduction vs baseline year | D10: Natural | E10: Environmental / climate | F10: Continuous (numeric) | G10: Integrated report, climate change section
A11: Renewable energy use | B11: Electricity/energy sourced from renewable generation (solar PV, wind, biomass, etc.) | C11: MWh | D11: Natural / Manufactured | E11: Environmental | F11: Continuous (numeric) | G11: Integrated report, environmental performance section
A12: Hazardous waste disposed | B12: Tonnes of hazardous waste sent for disposal (landfill, incineration, or licensed treatment) | C12: tonnes | D12: Natural | E12: Environmental | F12: Continuous (numeric) | G12: Integrated report, environmental performance section
... A21: Financial Year (FY) | B21: Company reporting year; note that fiscal year-ends differ (AECI, ArcelorMittal SA, Omnia and Sasol = 30 June or calendar; Sappi = year ended September) | C21: categorical (FY2021-FY2025) | D21: - | E21: Identifier | F21: Categorical | G21: -
A24: Exchange rates used for Sappi's USD-to-ZAR conversion
A26: Financial Year | B26: Average USD/ZAR rate | C26: Source
A27: FY2021 | B27: 14.7955 | C27: Nedbank Group Economic Unit, Annual Average Exchange Rates
A28: FY2022 | B28: 16.372 | C28: Nedbank Group Economic Unit, Annual Average Exchange Rates
A29: FY2023 | B29: 18.4519 | C29: Nedbank Group Economic Unit, Annual Average Exchange Rates
A30: FY2024 | B30: 18.3308 | C30: Nedbank Group Economic Unit, Annual Average Exchange Rates
A31: FY2025 | B31: 17.877 | C31: Nedbank Group Economic Unit, Annual Average Exchange Rates
A33: Note: Sappi's financial year ends 30 September; calendar-year average rates are used as a reasonable proxy for its fiscal year, disclosed here rather than treated as exact. Applying each year's own average rate (rather than a single constant rate) means the resulting % change in Rand terms reflects both Sappi's underlying US-dollar performance and the Rand's depreciation over the period (~21% from FY2021 to FY2025) — this is flagged explicitly wherever Sappi's Rand-converted trend is discussed in the written report.

Sheet ESG-Financial Risk Scorecard
A1: ESG-Adjusted Financial Risk Scorecard
A2: Digital/analytical artefact — Phase 5 (ESG-to-Financial-Risk Model). Value columns (C, D) are live formulas that look up the Dataset sheet by company, indicator and financial year (via Dataset!K, the auto-built lookup key), so correcting or extending the Dataset automatically updates this sheet. Blue cells = weight inputs (H), the only true judgement inputs in this model. Black cells = calculated. Yellow = data not yet available (see Notes) and defaulted to a neutral score of 3 rather than guessed.
A4: Company | B4: Indicator | C4: FY2021 value | D4: FY2025 value | E4: % change (FY21→FY25) | F4: Direction preferred | G4: Normalised score (1-5) 5=best | H4: Weight | I4: Weighted score | J4: Notes
A5: AECI | B5: Total carbon footprint (Scope 1+2, tCO2e) | C5: =IFERROR(INDEX(Dataset!$F$2:$F$1000,MATCH("AECI|Total carbon footprint (Scope 1+2)|FY2024",Dataset!$K$2:$K$1000,0)),"n/a") -> 416337 | D5: =IFERROR(INDEX(Dataset!$F$2:$F$1000,MATCH("AECI|Total carbon footprint (Scope 1+2)|FY2025",Dataset!$K$2:$K$1000,0)),"n/a") -> 365500 | E5: =IFERROR((D5-C5)/ABS(C5),"n/a") -> -0.12210541 | F5: down | G5: =IFERROR(MIN(5,MAX(1,3-(D5-C5)/ABS(C5)*5)),3) -> 3.610527 | H5: 0.2 | I5: =G5*H5 -> 0.72210541 | J5: FY2021 not disclosed in same basis; using FY2024=416,337 as prior-year comparator
A6: AECI | B6: TRIR (safety) | C6: =IFERROR(INDEX(Dataset!$F$2:$F$1000,MATCH("AECI|TRIR (Total Recordable Injury Rate)|FY2024",Dataset!$K$2:$K$1000,0)),"n/a") -> 0.31 | D6: =IFERROR(INDEX(Dataset!$F$2:$F$1000,MATCH("AECI|TRIR (Total Recordable Injury Rate)|FY2025",Dataset!$K$2:$K$1000,0)),"n/a") -> 0.2 | E6: =IFERROR((D6-C6)/ABS(C6),"n/a") -> -0.35483871 | F6: down | G6: =IFERROR(MIN(5,MAX(1,3-(D6-C6)/ABS(C6)*5)),3) -> 4.7741935 | H6: 0.15 | I6: =G6*H6 -> 0.71612903 | J6: FY2024 comparator = 0.31
A7: AECI | B7: EBITDA margin (%) | C7: =IFERROR(INDEX(Dataset!$F$2:$F$1000,MATCH("AECI|EBITDA margin|FY2024",Dataset!$K$2:$K$1000,0)),"n/a") -> 9 | D7: =IFERROR(INDEX(Dataset!$F$2:$F$1000,MATCH("AECI|EBITDA margin|FY2025",Dataset!$K$2:$K$1000,0)),"n/a") -> 11 | E7: =IFERROR((D7-C7)/ABS(C7),"n/a") -> 0.22222222 | F7: up | G7: =IFERROR(MIN(5,MAX(1,3+(D7-C7)/ABS(C7)*5)),3) -> 4.1111111 | H7: 0.2 | I7: =G7*H7 -> 0.82222222 | J7: FY2022 baseline used (FY2021 EBITDA margin not disclosed on comparable core basis)
A8: AECI | B8: ROIC (%) | C8: =IFERROR(INDEX(Dataset!$F$2:$F$1000,MATCH("AECI|ROIC|FY2024",Dataset!$K$2:$K$1000,0)),"n/a") -> 9 | D8: =IFERROR(INDEX(Dataset!$F$2:$F$1000,MATCH("AECI|ROIC|FY2025",Dataset!$K$2:$K$1000,0)),"n/a") -> 13 | E8: =IFERROR((D8-C8)/ABS(C8),"n/a") -> 0.44444444 | F8: up | G8: =IFERROR(MIN(5,MAX(1,3+(D8-C8)/ABS(C8)*5)),3) -> 5 | H8: 0.2 | I8: =G8*H8 -> 1 | J8: FY2022 baseline (strategy KPI table)
A9: AECI | B9: Female representation, management (%) | C9: =IFERROR(INDEX(Dataset!$F$2:$F$1000,MATCH("AECI|Female representation, top/senior/middle mgmt|FY2024",Dataset!$K$2:$K$1000,0)),"n/a") -> 29 | D9: =IFERROR(INDEX(Dataset!$F$2:$F$1000,MATCH("AECI|Female representation, top/senior/middle mgmt|FY2025",Dataset!$K$2:$K$1000,0)),"n/a") -> 30 | E9: =IFERROR((D9-C9)/ABS(C9),"n/a") -> 0.034482759 | F9: up | G9: =IFERROR(MIN(5,MAX(1,3+(D9-C9)/ABS(C9)*5)),3) -> 3.1724138 | H9: 0.15 | I9: =G9*H9 -> 0.47586207 | J9: FY2024 comparator = 29%
A10: AECI | B10: Net debt/EBITDA (x) | C10: =IFERROR(INDEX(Dataset!$F$2:$F$1000,MATCH("AECI|Net debt/EBITDA|FY2024",Dataset!$K$2:$K$1000,0)),"n/a") -> 1.2 | D10: =IFERROR(INDEX(Dataset!$F$2:$F$1000,MATCH("AECI|Net debt/EBITDA|FY2025",Dataset!$K$2:$K$1000,0)),"n/a") -> 0.1 | E10: =IFERROR((D10-C10)/ABS(C10),"n/a") -> -0.91666667 | F10: down | G10: =IFERROR(MIN(5,MAX(1,3-(D10-C10)/ABS(C10)*5)),3) -> 5 | H10: 0.1 | I10: =G10*H10 -> 0.5 | J10: FY2022 baseline
A11: AECI | B11: COMPOSITE ESG-ADJUSTED FINANCIAL RISK SCORE | I11: =SUM(I5:I10)/SUM(H5:H10) -> 4.2363187
A13: ArcelorMittal SA | B13: Fatalities | C13: =IFERROR(INDEX(Dataset!$F$2:$F$1000,MATCH("ArcelorMittal SA|Employee & contractor fatalities|FY2021",Dataset!$K$2:$K$1000,0)),"n/a") -> 6 | D13: =IFERROR(INDEX(Dataset!$F$2:$F$1000,MATCH("ArcelorMittal SA|Employee & contractor fatalities|FY2025",Dataset!$K$2:$K$1000,0)),"n/a") -> 1 | E13: =IFERROR((D13-C13)/ABS(C13),"n/a") -> -0.83333333 | F13: down | G13: =IFERROR(MIN(5,MAX(1,3-(D13-C13)/ABS(C13)*5)),3) -> 5 | H13: 0.2 | I13: =G13*H13 -> 1
A14: ArcelorMittal SA | B14: LTIFR | C14: =IFERROR(INDEX(Dataset!$F$2:$F$1000,MATCH("ArcelorMittal SA|LTIFR|FY2021",Dataset!$K$2:$K$1000,0)),"n/a") -> 0.98 | D14: =IFERROR(INDEX(Dataset!$F$2:$F$1000,MATCH("ArcelorMittal SA|LTIFR|FY2025",Dataset!$K$2:$K$1000,0)),"n/a") -> 0.62 | E14: =IFERROR((D14-C14)/ABS(C14),"n/a") -> -0.36734694 | F14: down | G14: =IFERROR(MIN(5,MAX(1,3-(D14-C14)/ABS(C14)*5)),3) -> 4.8367347 | H14: 0.15 | I14: =G14*H14 -> 0.7255102
A15: ArcelorMittal SA | B15: CO2 intensity (tCO2e/t liquid steel) | C15: =IFERROR(INDEX(Dataset!$F$2:$F$1000,MATCH("ArcelorMittal SA|CO2 emissions intensity|FY2021",Dataset!$K$2:$K$1000,0)),"n/a") -> 2.72 | D15: =IFERROR(INDEX(Dataset!$F$2:$F$1000,MATCH("ArcelorMittal SA|CO2 emissions intensity|FY2025",Dataset!$K$2:$K$1000,0)),"n/a") -> 3.26 | E15: =IFERROR((D15-C15)/ABS(C15),"n/a") -> 0.19852941 | F15: down | G15: =IFERROR(MIN(5,MAX(1,3-(D15-C15)/ABS(C15)*5)),3) -> 2.0073529 | H15: 0.2 | I15: =G15*H15 -> 0.40147059 | J15: Intensity worsened FY21-FY25
A16: ArcelorMittal SA | B16: Return on capital employed (%) | C16: =IFERROR(INDEX(Dataset!$F$2:$F$1000,MATCH("ArcelorMittal SA|Return on capital employed|FY2021",Dataset!$K$2:$K$1000,0)),"n/a") -> 53.9 | D16: =IFERROR(INDEX(Dataset!$F$2:$F$1000,MATCH("ArcelorMittal SA|Return on capital employed|FY2025",Dataset!$K$2:$K$1000,0)),"n/a") -> -16.07 | E16: =IFERROR((D16-C16)/ABS(C16),"n/a") -> -1.2981447 | F16: up | G16: =IFERROR(MIN(5,MAX(1,3+(D16-C16)/ABS(C16)*5)),3) -> 1 | H16: 0.25 | I16: =G16*H16 -> 0.25 | J16: Sharp deterioration
A17: ArcelorMittal SA | B17: B-BBEE compliance score | C17: =IFERROR(INDEX(Dataset!$F$2:$F$1000,MATCH("ArcelorMittal SA|B-BBEE compliance score|FY2021",Dataset!$K$2:$K$1000,0)),"n/a") -> 8 | D17: =IFERROR(INDEX(Dataset!$F$2:$F$1000,MATCH("ArcelorMittal SA|B-BBEE compliance score|FY2025",Dataset!$K$2:$K$1000,0)),"n/a") -> 4 | E17: =IFERROR((D17-C17)/ABS(C17),"n/a") -> -0.5 | F17: up | G17: =IFERROR(MIN(5,MAX(1,3+(D17-C17)/ABS(C17)*5)),3) -> 1 | H17: 0.1 | I17: =G17*H17 -> 0.1 | J17: Score declined (self-assessed FY2025)
A18: ArcelorMittal SA | B18: Net debt (Rm) | C18: =IFERROR(INDEX(Dataset!$F$2:$F$1000,MATCH("ArcelorMittal SA|Net debt position|FY2021",Dataset!$K$2:$K$1000,0)),"n/a") -> 1258 | D18: =IFERROR(INDEX(Dataset!$F$2:$F$1000,MATCH("ArcelorMittal SA|Net debt position|FY2025",Dataset!$K$2:$K$1000,0)),"n/a") -> 6763 | E18: =IFERROR((D18-C18)/ABS(C18),"n/a") -> 4.3759936 | F18: down | G18: =IFERROR(MIN(5,MAX(1,3-(D18-C18)/ABS(C18)*5)),3) -> 1 | H18: 0.1 | I18: =G18*H18 -> 0.1 | J18: Rising net debt
A19: ArcelorMittal SA | B19: COMPOSITE ESG-ADJUSTED FINANCIAL RISK SCORE | I19: =SUM(I13:I18)/SUM(H13:H18) -> 2.5769808
A21: Omnia | B21: Scope 1 GHG emissions (t) | C21: =IFERROR(INDEX(Dataset!$F$2:$F$1000,MATCH("Omnia|Scope 1 GHG emissions|FY2021",Dataset!$K$2:$K$1000,0)),"n/a") -> 178139 | D21: =IFERROR(INDEX(Dataset!$F$2:$F$1000,MATCH("Omnia|Scope 1 GHG emissions|FY2025",Dataset!$K$2:$K$1000,0)),"n/a") -> 70437 | E21: =IFERROR((D21-C21)/ABS(C21),"n/a") -> -0.60459529 | F21: down | G21: =IFERROR(MIN(5,MAX(1,3-(D21-C21)/ABS(C21)*5)),3) -> 5 | H21: 0.2 | I21: =G21*H21 -> 1
A22: Omnia | B22: Scope 2 GHG emissions (t) | C22: =IFERROR(INDEX(Dataset!$F$2:$F$1000,MATCH("Omnia|Scope 2 GHG emissions|FY2021",Dataset!$K$2:$K$1000,0)),"n/a") -> 83361 | D22: =IFERROR(INDEX(Dataset!$F$2:$F$1000,MATCH("Omnia|Scope 2 GHG emissions|FY2025",Dataset!$K$2:$K$1000,0)),"n/a") -> 69960 | E22: =IFERROR((D22-C22)/ABS(C22),"n/a") -> -0.16075863 | F22: down | G22: =IFERROR(MIN(5,MAX(1,3-(D22-C22)/ABS(C22)*5)),3) -> 3.8037931 | H22: 0.15 | I22: =G22*H22 -> 0.57056897
A23: Omnia | B23: Revenue (Rm) | C23: =IFERROR(INDEX(Dataset!$F$2:$F$1000,MATCH("Omnia|Revenue|FY2021",Dataset!$K$2:$K$1000,0)),"n/a") -> 16436 | D23: =IFERROR(INDEX(Dataset!$F$2:$F$1000,MATCH("Omnia|Revenue|FY2025",Dataset!$K$2:$K$1000,0)),"n/a") -> 22818 | E23: =IFERROR((D23-C23)/ABS(C23),"n/a") -> 0.38829399 | F23: up | G23: =IFERROR(MIN(5,MAX(1,3+(D23-C23)/ABS(C23)*5)),3) -> 4.9414699 | H23: 0.2 | I23: =G23*H23 -> 0.98829399
A24: Omnia | B24: Headline earnings per share (cents) | C24: =IFERROR(INDEX(Dataset!$F$2:$F$1000,MATCH("Omnia|Headline earnings per share|FY2021",Dataset!$K$2:$K$1000,0)),"n/a") -> 361 | D24: =IFERROR(INDEX(Dataset!$F$2:$F$1000,MATCH("Omnia|Headline earnings per share|FY2025",Dataset!$K$2:$K$1000,0)),"n/a") -> 704 | E24: =IFERROR((D24-C24)/ABS(C24),"n/a") -> 0.9501385 | F24: up | G24: =IFERROR(MIN(5,MAX(1,3+(D24-C24)/ABS(C24)*5)),3) -> 5 | H24: 0.25 | I24: =G24*H24 -> 1.25
A25: Omnia | B25: Recordable case rate | C25: =IFERROR(INDEX(Dataset!$F$2:$F$1000,MATCH("Omnia|Recordable case rate (RCR)|FY2024",Dataset!$K$2:$K$1000,0)),"n/a") -> 0.05 | D25: =IFERROR(INDEX(Dataset!$F$2:$F$1000,MATCH("Omnia|Recordable case rate (RCR)|FY2025",Dataset!$K$2:$K$1000,0)),"n/a") -> 0.2 | E25: =IFERROR((D25-C25)/ABS(C25),"n/a") -> 3 | F25: down | G25: =IFERROR(MIN(5,MAX(1,3-(D25-C25)/ABS(C25)*5)),3) -> 1 | H25: 0.1 | I25: =G25*H25 -> 0.1 | J25: FY2024 comparator = 0.05 (deteriorated)
A26: Omnia | B26: Renewable energy use (MWh) | C26: =IFERROR(INDEX(Dataset!$F$2:$F$1000,MATCH("Omnia|Renewable energy use|FY2024",Dataset!$K$2:$K$1000,0)),"n/a") -> 12976 | D26: =IFERROR(INDEX(Dataset!$F$2:$F$1000,MATCH("Omnia|Renewable energy use|FY2025",Dataset!$K$2:$K$1000,0)),"n/a") -> 20109 | E26: =IFERROR((D26-C26)/ABS(C26),"n/a") -> 0.54970715 | F26: up | G26: =IFERROR(MIN(5,MAX(1,3+(D26-C26)/ABS(C26)*5)),3) -> 5 | H26: 0.1 | I26: =G26*H26 -> 0.5 | J26: FY2024 comparator = 12,976
A27: Omnia | B27: COMPOSITE ESG-ADJUSTED FINANCIAL RISK SCORE | I27: =SUM(I21:I26)/SUM(H21:H26) -> 4.408863
A29: Sappi | B29: Sales (Rm, converted from USD) | C29: =IFERROR(INDEX(Dataset!$F$2:$F$1000,MATCH("Sappi|Sales|FY2021",Dataset!$K$2:$K$1000,0)),"n/a") -> 77898 | D29: =IFERROR(INDEX(Dataset!$F$2:$F$1000,MATCH("Sappi|Sales|FY2025",Dataset!$K$2:$K$1000,0)),"n/a") -> 96893 | E29: =IFERROR((D29-C29)/ABS(C29),"n/a") -> 0.24384451 | F29: up | G29: =IFERROR(MIN(5,MAX(1,3+(D29-C29)/ABS(C29)*5)),3) -> 4.2192226 | H29: 0.15 | I29: =G29*H29 -> 0.63288339 | J29: Converted from US$m using OECD/FRED annual average USD/ZAR rate per year; Rand-weakness over the period makes this figure more favourable than the original USD trend.
A30: Sappi | B30: Adjusted EBITDA (Rm, converted from USD) | C30: =IFERROR(INDEX(Dataset!$F$2:$F$1000,MATCH("Sappi|Adjusted EBITDA|FY2021",Dataset!$K$2:$K$1000,0)),"n/a") -> 7871 | D30: =IFERROR(INDEX(Dataset!$F$2:$F$1000,MATCH("Sappi|Adjusted EBITDA|FY2025",Dataset!$K$2:$K$1000,0)),"n/a") -> 8956 | E30: =IFERROR((D30-C30)/ABS(C30),"n/a") -> 0.1378478 | F30: up | G30: =IFERROR(MIN(5,MAX(1,3+(D30-C30)/ABS(C30)*5)),3) -> 3.689239 | H30: 0.25 | I30: =G30*H30 -> 0.92230974 | J30: Converted from US$m; up 13.9% in Rand terms over FY2021-FY2025, versus down 5.8% in the original USD figures, due to Rand depreciation over the period.
A31: Sappi | B31: Headline earnings/(loss) per share (cents, converted from USD) | C31: =IFERROR(INDEX(Dataset!$F$2:$F$1000,MATCH("Sappi|Headline earnings/(loss) per share|FY2021",Dataset!$K$2:$K$1000,0)),"n/a") -> 74 | D31: =IFERROR(INDEX(Dataset!$F$2:$F$1000,MATCH("Sappi|Headline earnings/(loss) per share|FY2025",Dataset!$K$2:$K$1000,0)),"n/a") -> -268 | E31: =IFERROR((D31-C31)/ABS(C31),"n/a") -> -4.6216216 | F31: up | G31: =IFERROR(MIN(5,MAX(1,3+(D31-C31)/ABS(C31)*5)),3) -> 1 | H31: 0.25 | I31: =G31*H31 -> 0.25 | J31: Converted from US cents; still turns negative in FY2025 in both currencies.
A32: Sappi | B32: Net asset value per share (cents, converted from USD) | C32: =IFERROR(INDEX(Dataset!$F$2:$F$1000,MATCH("Sappi|Net asset value per share|FY2021",Dataset!$K$2:$K$1000,0)),"n/a") -> 5193 | D32: =IFERROR(INDEX(Dataset!$F$2:$F$1000,MATCH("Sappi|Net asset value per share|FY2025",Dataset!$K$2:$K$1000,0)),"n/a") -> 6829 | E32: =IFERROR((D32-C32)/ABS(C32),"n/a") -> 0.31503948 | F32: up | G32: =IFERROR(MIN(5,MAX(1,3+(D32-C32)/ABS(C32)*5)),3) -> 4.5751974 | H32: 0.15 | I32: =G32*H32 -> 0.68627961 | J32: Converted from US cents; up 31.6% in Rand terms, versus up 8.8% in USD, due to Rand depreciation.
A33: Sappi | B33: Profit/(loss) for the year (Rm, converted from USD) | C33: =IFERROR(INDEX(Dataset!$F$2:$F$1000,MATCH("Sappi|Profit/(loss) for the year|FY2021",Dataset!$K$2:$K$1000,0)),"n/a") -> 192 | D33: =IFERROR(INDEX(Dataset!$F$2:$F$1000,MATCH("Sappi|Profit/(loss) for the year|FY2025",Dataset!$K$2:$K$1000,0)),"n/a") -> -3164 | E33: =IFERROR((D33-C33)/ABS(C33),"n/a") -> -17.479167 | F33: up | G33: =IFERROR(MIN(5,MAX(1,3+(D33-C33)/ABS(C33)*5)),3) -> 1 | H33: 0.2 | I33: =G33*H33 -> 0.2 | J33: Converted from US$m; still swings to a loss in FY2025 in both currencies.
A34: Sappi | B34: COMPOSITE ESG-ADJUSTED FINANCIAL RISK SCORE | I34: =SUM(I29:I33)/SUM(H29:H33) -> 2.6914727
A36: Sasol | B36: GHG reduction vs FY2017 baseline (%) | C36: n/a | D36: =IFERROR(INDEX(Dataset!$F$2:$F$1000,MATCH("Sasol|GHG emission reduction vs FY2017 baseline (International Chemicals)|FY2025",Dataset!$K$2:$K$1000,0)),"n/a") -> 23 | E36: =IFERROR((D36-C36)/ABS(C36),"n/a") -> n/a | F36: up | G36: =IFERROR(MIN(5,MAX(1,3+(D36-C36)/ABS(C36)*5)),3) -> 3 | H36: 0.3 | I36: =G36*H36 -> 0.9 | J36: Group target 30% by 2030; FY2025 figure is for International Chemicals only (p.85)
A37: Sasol | B37: Fatalities | C37: =IFERROR(INDEX(Dataset!$F$2:$F$1000,MATCH("Sasol|Fatalities|FY2022",Dataset!$K$2:$K$1000,0)),"n/a") -> 5 | D37: =IFERROR(INDEX(Dataset!$F$2:$F$1000,MATCH("Sasol|Fatalities|FY2024",Dataset!$K$2:$K$1000,0)),"n/a") -> 6 | E37: =IFERROR((D37-C37)/ABS(C37),"n/a") -> 0.2 | F37: down | G37: =IFERROR(MIN(5,MAX(1,3-(D37-C37)/ABS(C37)*5)),3) -> 2 | H37: 0.3 | I37: =G37*H37 -> 0.6 | J37: FY2022 vs FY2024 (most recent disclosed); FY2025 not yet extracted
A38: Sasol | B38: Recordable case rate | C38: n/a | D38: =IFERROR(INDEX(Dataset!$F$2:$F$1000,MATCH("Sasol|Recordable case rate|FY2024",Dataset!$K$2:$K$1000,0)),"n/a") -> 0.25 | E38: =IFERROR((D38-C38)/ABS(C38),"n/a") -> n/a | F38: down | G38: =IFERROR(MIN(5,MAX(1,3-(D38-C38)/ABS(C38)*5)),3) -> 3 | H38: 0.2 | I38: =G38*H38 -> 0.6 | J38: FY2024 only; time series incomplete
A39: Sasol | B39: External turnover (Rm) | C39: =IFERROR(INDEX(Dataset!$F$2:$F$1000,MATCH("Sasol|External turnover|FY2021",Dataset!$K$2:$K$1000,0)),"n/a") -> 201910 | D39: =IFERROR(INDEX(Dataset!$F$2:$F$1000,MATCH("Sasol|External turnover|FY2025",Dataset!$K$2:$K$1000,0)),"n/a") -> 249096 | E39: =IFERROR((D39-C39)/ABS(C39),"n/a") -> 0.23369818 | F39: up | G39: =IFERROR(MIN(5,MAX(1,3+(D39-C39)/ABS(C39)*5)),3) -> 4.1684909 | H39: 0.15 | I39: =G39*H39 -> 0.62527364 | J39: Sourced from Sasol's audited SENS/PRNewswire results announcements.
A40: Sasol | B40: Adjusted EBITDA (Rm) | C40: =IFERROR(INDEX(Dataset!$F$2:$F$1000,MATCH("Sasol|Adjusted EBITDA|FY2021",Dataset!$K$2:$K$1000,0)),"n/a") -> 48420 | D40: =IFERROR(INDEX(Dataset!$F$2:$F$1000,MATCH("Sasol|Adjusted EBITDA|FY2025",Dataset!$K$2:$K$1000,0)),"n/a") -> 51764 | E40: n/a | F40: up | G40: 3 | H40: 0.2 | I40: =G40*H40 -> 0.6 | J40: Now sourced from Sasol's audited SENS/PRNewswire results announcements (external to the integrated reports) since no 5-year table exists in the integrated reports themselves.
A41: Sasol | B41: COMPOSITE ESG-ADJUSTED FINANCIAL RISK SCORE | I41: =SUM(I36:I40)/SUM(H36:H40) -> 2.8915423
A44: Summary: composite score by company (5 = strongest ESG-adjusted position, 1 = weakest)
A45: AECI | B45: =I11 -> 4.2363187
A46: ArcelorMittal SA | B46: =I19 -> 2.5769808
A47: Omnia | B47: =I27 -> 4.408863
A48: Sappi | B48: =I34 -> 2.6914727
A49: Sasol | B49: =I41 -> 2.8915423
